dop3/__init__.py
dop3/predictor.py
dop3-0.1.1.dist-info/METADATA
dop3-0.1.1.dist-info/WHEEL
dop3-0.1.1.dist-info/RECORD
