Metadata-Version: 2.4
Name: dop3
Version: 0.1.1
Summary: DFUai is a Python package that uses AI to assist clinical doctors in diagnosing the severity of diabetic foot ulcers. It classifies diabetic foot severity (mild, moderate, or severe) based on eight clinical features: PAD, CRP, HbA1c, DKD, ESR, ALB, SBP, and X25OHD.
Author: ycj
Author-email: yanchangjian2019@126.com
Requires-Python: >=3.7
Classifier: Programming Language :: Python :: 3
Classifier: Programming Language :: Python :: 3.7
Classifier: Programming Language :: Python :: 3.8
Classifier: Programming Language :: Python :: 3.9
Classifier: Programming Language :: Python :: 3.10
Classifier: Programming Language :: Python :: 3.11
Classifier: Programming Language :: Python :: 3.12
Classifier: Programming Language :: Python :: 3.13
Classifier: Programming Language :: Python :: 3.14
